manonaid_helpers/__init__.py
manonaid_helpers/checks.py
manonaid_helpers/core.py
manonaid_helpers/download.py
manonaid_helpers/utils.py
manonaid_helpers-0.1.4.dist-info/LICENSE
manonaid_helpers-0.1.4.dist-info/METADATA
manonaid_helpers-0.1.4.dist-info/WHEEL
manonaid_helpers-0.1.4.dist-info/top_level.txt
manonaid_helpers-0.1.4.dist-info/RECORD
