Metadata-Version: 2.1
Name: manonaid-helpers
Version: 0.1.4
Summary: A small example package
Author: manonaid
Author-email: manoharan.naidu@gmail.com
Classifier: Programming Language :: Python :: 3
Requires-Python: >=3.7
License-File: LICENSE
Requires-Dist: azure-storage-blob
Requires-Dist: pandas
